topo_cicd_test/__init__.py
topo_cicd_test/run.py
topo_cicd_test-0.1.18.dist-info/METADATA
topo_cicd_test-0.1.18.dist-info/WHEEL
topo_cicd_test-0.1.18.dist-info/entry_points.txt
topo_cicd_test-0.1.18.dist-info/licenses/LICENSE
topo_cicd_test-0.1.18.dist-info/RECORD
