Metadata-Version: 2.1
Name: topo-cicd-test
Version: 0.1.18
Summary: A simple Python project to demonstrate CI/CD with Hatch.
Author-email: Your Name <tvallas@iki.fi>
License: MIT
License-File: LICENSE
Requires-Python: >=3.6
